kingbot/__init__.py
kingbot/__main__.py
kingbot/plugins/__init__.py
kingbot/plugins/hel__p.py
sql_helper/__init__.py
sql_helper/afk.py
sql_helper/autopostingdb.py
sql_helper/gbandb.py
sql_helper/gmutedb.py
sql_helper/permit.py
uti/__init__.py
uti/confi.py
uti/errors.py
uti/misc.py
uti/serra.py
py_kinguserbot-1.9.dist-info/METADATA
py_kinguserbot-1.9.dist-info/WHEEL
py_kinguserbot-1.9.dist-info/top_level.txt
py_kinguserbot-1.9.dist-info/RECORD
