Metadata-Version: 2.1
Name: py-kinguserbot
Version: 1.9
Summary: A Secure and Powerful Python-PyrogramBased Library For Kingbot .
Home-page: https://github.com/ToxicCyber/kinguserbot
Author: TeamDevil
Author-email: De.codes.official@gmail.com
License: GNU AFFERO GENERAL PUBLIC LICENSE (v3)
Platform: UNKNOWN
Classifier: Programming Language :: Python :: 3
Classifier: License :: OSI Approved :: GNU General Public License v3 (GPLv3)
Classifier: Operating System :: OS Independent
Requires-Python: >=3.6
Requires-Dist: pyrogram
Requires-Dist: redis
Requires-Dist: python-decouple (==3.3)
Requires-Dist: TgCrypto (==1.2.2)
Requires-Dist: python-dotenv (==0.15.0)
Requires-Dist: sqlalchemy
Requires-Dist: heroku3
